MANIFEST.in
README.rst
setup.py
mingle/__init__.py
mingle/command.py
mingle/io.py
mingle/parser.py
mingle.egg-info/PKG-INFO
mingle.egg-info/SOURCES.txt
mingle.egg-info/dependency_links.txt
mingle.egg-info/entry_points.txt
mingle.egg-info/not-zip-safe
mingle.egg-info/requires.txt
mingle.egg-info/top_level.txt