Metadata-Version: 1.1
Name: mingle
Version: 0.1.3
Summary: Get lines from a number of log files with different time-stamp formats in chronological order
Home-page: https://bitbucket.org/swbclarke/mingle
Author: Sebastian Clarke
Author-email: swb@rift.team
License: MIT
Download-URL: https://bitbucket.org/swbclarke/mingle/get/0.1.3.tar.gz
Platform: UNKNOWN
Classifier: Development Status :: 3 - Alpha
Classifier: Environment :: Console
Classifier: Intended Audience :: Developers
Classifier: Intended Audience :: Information Technology
Classifier: Intended Audience :: System Administrators
Classifier: License :: OSI Approved :: GNU General Public License v3 or later (GPLv3+)
Classifier: Natural Language :: English
Classifier: Programming Language :: Python :: 2.7
Classifier: Programming Language :: Python :: 3
Classifier: Topic :: Software Development :: Bug Tracking
Classifier: Topic :: System :: Logging
Classifier: Topic :: System :: Monitoring
Classifier: Topic :: System :: Systems Administration
Classifier: Topic :: Text Processing
Classifier: Topic :: Text Processing :: Indexing
Classifier: Topic :: Utilities
